{
    "key": "group_5bbea7aea203f",
    "title": "Markup: Animation",
    "fields": [
        {
            "key": "field_5bbea7de20835__trashed",
            "label": "Show",
            "name": "show",
            "type": "true_false",
            "instructions": "",
            "required": 0,
            "conditional_logic": 0,
            "wrapper": {
                "width": "50",
                "class": "",
                "id": ""
            },
            "message": "",
            "default_value": 0,
            "ui": 0,
            "ui_on_text": "",
            "ui_off_text": ""
        },
        {
            "key": "field_5bbea81b20836__trashed",
            "label": "Infinite",
            "name": "infinite",
            "type": "true_false",
            "instructions": "",
            "required": 0,
            "conditional_logic": [
                [
                    {
                        "field": "field_5bbea7de20835",
                        "operator": "==",
                        "value": "1"
                    }
                ]
            ],
            "wrapper": {
                "width": "50",
                "class": "",
                "id": ""
            },
            "message": "",
            "default_value": 0,
            "ui": 0,
            "ui_on_text": "",
            "ui_off_text": ""
        },
        {
            "key": "field_5bbea8b420838__trashed",
            "label": "Speed",
            "name": "speed",
            "type": "select",
            "instructions": "",
            "required": 0,
            "conditional_logic": [
                [
                    {
                        "field": "field_5bbea7de20835",
                        "operator": "==",
                        "value": "1"
                    }
                ]
            ],
            "wrapper": {
                "width": "50",
                "class": "",
                "id": ""
            },
            "choices": {
                "default": "Default",
                "slow": "Slow",
                "slower": "slower",
                "fast": "Fast",
                "faster": "Faster"
            },
            "default_value": [],
            "allow_null": 0,
            "multiple": 0,
            "ui": 0,
            "return_format": "value",
            "ajax": 0,
            "placeholder": ""
        },
        {
            "key": "field_5bbea92920839__trashed",
            "label": "Delay",
            "name": "delay",
            "type": "select",
            "instructions": "",
            "required": 0,
            "conditional_logic": [
                [
                    {
                        "field": "field_5bbea7de20835",
                        "operator": "==",
                        "value": "1"
                    }
                ]
            ],
            "wrapper": {
                "width": "50",
                "class": "",
                "id": ""
            },
            "choices": {
                "default": "Default",
                "delay-2s": "2s",
                "delay-3s": "3s",
                "delay-4s": "4s",
                "delay-5s": "5s"
            },
            "default_value": [
                "default"
            ],
            "allow_null": 0,
            "multiple": 0,
            "ui": 0,
            "return_format": "value",
            "ajax": 0,
            "placeholder": ""
        },
        {
            "key": "field_5bbea84220837__trashed",
            "label": "Animation Name",
            "name": "name",
            "type": "text",
            "instructions": "Find the name of the animation <a href=\"https:\/\/daneden.github.io\/animate.css\/\">here<\/a>",
            "required": 0,
            "conditional_logic": [
                [
                    {
                        "field": "field_5bbea7de20835",
                        "operator": "==",
                        "value": "1"
                    }
                ]
            ],
            "wrapper": {
                "width": "",
                "class": "",
                "id": ""
            },
            "default_value": "fadeInUp",
            "placeholder": "",
            "prepend": "",
            "append": "",
            "maxlength": ""
        }
    ],
    "location": [],
    "menu_order": 0,
    "position": "normal",
    "style": "default",
    "label_placement": "top",
    "instruction_placement": "label",
    "hide_on_screen": "",
    "active": 1,
    "description": "",
    "is_acf_component": 1,
    "acf_component_defaults": {
        "repeatable": "0",
        "min": "",
        "max": "",
        "layout": "block",
        "button_label": "",
        "appearances": ""
    },
    "modified": 1542069747
}